sqwishai/__init__.py
sqwishai-0.0.1.dist-info/METADATA
sqwishai-0.0.1.dist-info/WHEEL
sqwishai-0.0.1.dist-info/top_level.txt
sqwishai-0.0.1.dist-info/RECORD
