Metadata-Version: 2.1
Name: sqwishai
Version: 0.0.1
Summary: Coming soon
Author-email: Sqwish - Federica <federica@sqwish.ai>
